cathealthpy/__init__.py
cathealthpy/advisor.py
cathealthpy/analyzer.py
cathealthpy/tracker.py
cathealthpy/visualizer.py
cathealthpy-0.1.0.dist-info/METADATA
cathealthpy-0.1.0.dist-info/WHEEL
cathealthpy-0.1.0.dist-info/top_level.txt
cathealthpy-0.1.0.dist-info/RECORD
