Metadata-Version: 2.1
Name: cathealthpy
Version: 0.1.0
Summary: A package for tracking and analyzing cat health data
Home-page: https://github.com/FurutaAika/cathealthpy
Author: Aika
Author-email: s2222093@stu.musashino-u.ac.jp
Classifier: Programming Language :: Python :: 3
Classifier: License :: OSI Approved :: MIT License
Classifier: Operating System :: OS Independent
Requires-Python: >=3.6
Requires-Dist: matplotlib
